Workbook
Name Slicer_Country: #N/A
Name Slicer_Month: #N/A
Name Slicer_Region: #N/A

Sheet Raw_Data
A1: JE Code | B1: Store | C1: Country | D1: Region | E1: Date | F1: Item | G1: Salesperson | H1: List Price | I1: Actual Price | J1: Discount % | K1: Quantity | L1: Revenue
A2: I-1001 | B2: Moscow | C2: Russia | D2: EMEA | E2: 43261 | F2: Microwave | G2: May Wilmot | H2: 80 | I2: 79 | J2: 0.0125 | K2: 83 | L2: =tblSales[[#This Row],[Quantity]]*tblSales[[#This Row],[Actual Price]] -> 6557
A3: I-1002 | B3: Toronto | C3: Canada | D3: NA | E3: 42117 | F3: Microwave | G3: David Shiner | H3: 80 | I3: 54 | J3: 0.325 | K3: 8 | L3: =tblSales[[#This Row],[Quantity]]*tblSales[[#This Row],[Actual Price]] -> 432
A4: I-1003 | B4: Sao Paolo | C4: Brazil | D4: LATAM | E4: 42798 | F4: Air conditioner | G4: Gary Reynolds | H4: 700 | I4: 686 | J4: 0.02 | K4: 91 | L4: =tblSales[[#This Row],[Quantity]]*tblSales[[#This Row],[Actual Price]] -> 62426
A5: I-1004 | B5: Istanbul | C5: Turkey | D5: EMEA | E5: 43326 | F5: Ceiling fan | G5: Mark Buntain | H5: 150 | I5: 137 | J5: 0.0867 | K5: 2 | L5: =tblSales[[#This Row],[Quantity]]*tblSales[[#This Row],[Actual Price]] -> 274
A6: I-1005 | B6: Sydney | C6: Australia | D6: APAC | E6: 42066 | F6: Toaster | G6: Christine Davies | H6: 50 | I6: 37 | J6: 0.26 | K6: 40 | L6: =tblSales[[#This Row],[Quantity]]*tblSales[[#This Row],[Actual Price]] -> 1480
A7: I-1006 | B7: Shenzhen | C7: China | D7: APAC | E7: 42485 | F7: Iron | G7: Gary Shaw | H7: 30 | I7: 29 | J7: 0.0333 | K7: 27 | L7: =tblSales[[#This Row],[Quantity]]*tblSales[[#This Row],[Actual Price]] -> 783
A8: I-1007 | B8: Lima | C8: Peru | D8: LATAM | E8: 42527 | F8: Dishwasher | G8: Christopher Cresswell | H8: 500 | I8: 465 | J8: 0.07 | K8: 70
A9: I-1008 | B9: Tijuana | C9: Mexico | D9: LATAM | E9: 42557 | F9: Iron | G9: Gillian Allnutt | H9: 30 | I9: 28 | J9: 0.0667 | K9: 42 | L9: =tblSales[[#This Row],[Quantity]]*tblSales[[#This Row],[Actual Price]] -> 1176
A10: I-1009 | B10: London | C10: UK | D10: EMEA | E10: 42320 | F10: Washing Machine | G10: Francis Godden | H10: 800 | I10: 760 | J10: 0.05 | K10: 76 | L10: =tblSales[[#This Row],[Quantity]]*tblSales[[#This Row],[Actual Price]] -> 57760
A11: I-1010 | B11: Lima | C11: Peru | D11: LATAM | E11: 41829 | F11: Iron | G11: Christopher Cresswell | H11: 30 | I11: 28 | J11: 0.0667 | K11: 68 | L11: =tblSales[[#This Row],[Quantity]]*tblSales[[#This Row],[Actual Price]] -> 1904
A12: I-1011 | B12: Riyadh | C12: Saudi Arabia | D12: EMEA | E12: 42926 | F12: Refrigerator | G12: Danny Brooks | H12: 1000 | I12: 500 | J12: 0.5 | K12: 52 | L12: =tblSales[[#This Row],[Quantity]]*tblSales[[#This Row],[Actual Price]] -> 26000
A13: I-1012 | B13: Bangkok | C13: Thailand | D13: APAC | E13: 41872 | F13: Air conditioner | G13: John Jenkins | H13: 700 | I13: 679 | J13: 0.03 | K13: 71 | L13: =tblSales[[#This Row],[Quantity]]*tblSales[[#This Row],[Actual Price]] -> 48209
A14: I-1013 | B14: Tijuana | C14: Mexico | D14: LATAM | E14: 42250 | F14: Iron | G14: Richard Allnutt | H14: 30 | I14: 28 | J14: 0.0667 | K14: 5 | L14: =tblSales[[#This Row],[Quantity]]*tblSales[[#This Row],[Actual Price]] -> 140
A15: I-1014 | B15: Delhi | C15: India | D15: APAC | E15: 41789 | F15: Oven | G15: Tessa Morrow | H15: 500 | I15: 490 | J15: 0.02 | K15: 57 | L15: =tblSales[[#This Row],[Quantity]]*tblSales[[#This Row],[Actual Price]] -> 27930
A16: I-1015 | B16: Sydney | C16: Australia | D16: APAC | E16: 43445 | F16: Washing Machine | G16: James Ricketts | H16: 800 | I16: 672 | J16: 0.16 | K16: 1 | L16: =tblSales[[#This Row],[Quantity]]*tblSales[[#This Row],[Actual Price]] -> 672
A17: I-1016 | B17: Ho Chi Minh City | C17: Vietnam | D17: APAC | E17: 42148 | F17: Microwave | G17: Susan Dixon | H17: 80 | I17: 78 | J17: 0.025 | K17: 11 | L17: =tblSales[[#This Row],[Quantity]]*tblSales[[#This Row],[Actual Price]] -> 858
A18: I-1017 | B18: Tel Aviv | C18: Israel | D18: EMEA | E18: 41802 | F18: Refrigerator | G18: Thomas Gordon | H18: 1000 | I18: 620 | J18: 0.38 | K18: 45 | L18: =tblSales[[#This Row],[Quantity]]*tblSales[[#This Row],[Actual Price]] -> 27900
A19: I-1018 | B19: Athens | C19: Greece | D19: EMEA | E19: 43046 | F19: Oven | G19: David Walker | H19: 500 | I19: 500 | J19: 0 | K19: 59 | L19: =tblSales[[#This Row],[Quantity]]*tblSales[[#This Row],[Actual Price]] -> 29500
A20: I-1019 | B20: Toronto | C20: Canada | D20: NA | E20: 41946 | F20: Ceiling fan | G20: Robin Hall | H20: 150 | I20: 150 | J20: 0 | K20: 5 | L20: =tblSales[[#This Row],[Quantity]]*tblSales[[#This Row],[Actual Price]] -> 750
... A2340: I-3339 | B2340: Shanghai | C2340: China | D2340: APAC | E2340: 42980 | F2340: Microwave | G2340: Glenys Raymond | H2340: 80 | I2340: 77 | J2340: 0.0375 | K2340: 23 | L2340: =tblSales[[#This Row],[Quantity]]*tblSales[[#This Row],[Actual Price]] -> 1771

Sheet Sheet1
A1: JE Code | B1: =VLOOKUP(A1,Raw_Data!A:L,6,FALSE) -> Item | C1: =VLOOKUP(A1,Raw_Data!A:L,3,FALSE) -> Country | D1: =VLOOKUP(A1,Raw_Data!A:L,12,FALSE) -> Revenue | E1: =VLOOKUP(A1,Raw_Data!A:L,11,FALSE) -> Quantity | F1: =TEXT(VLOOKUP(A1,Raw_Data!A:L,5,FALSE),"mmm") -> Date
A2: I-1001 | B2: =VLOOKUP(A2,Raw_Data!A:L,6,FALSE) -> Microwave | C2: =VLOOKUP(A2,Raw_Data!A:L,3,FALSE) -> Russia | D2: =VLOOKUP(A2,Raw_Data!A:L,12,FALSE) -> 6557 | E2: =VLOOKUP(A2,Raw_Data!A:L,11,FALSE) -> 83 | F2: =TEXT(VLOOKUP(A2,Raw_Data!A:L,5,FALSE),"mmm") -> Jun
A3: I-1002 | B3: =VLOOKUP(A3,Raw_Data!A:L,6,FALSE) -> Microwave | C3: =VLOOKUP(A3,Raw_Data!A:L,3,FALSE) -> Canada | D3: =VLOOKUP(A3,Raw_Data!A:L,12,FALSE) -> 432 | E3: =VLOOKUP(A3,Raw_Data!A:L,11,FALSE) -> 8 | F3: =TEXT(VLOOKUP(A3,Raw_Data!A:L,5,FALSE),"mmm") -> Apr
A4: I-1003 | B4: =VLOOKUP(A4,Raw_Data!A:L,6,FALSE) -> Air conditioner | C4: =VLOOKUP(A4,Raw_Data!A:L,3,FALSE) -> Brazil | D4: =VLOOKUP(A4,Raw_Data!A:L,12,FALSE) -> 62426 | E4: =VLOOKUP(A4,Raw_Data!A:L,11,FALSE) -> 91 | F4: =TEXT(VLOOKUP(A4,Raw_Data!A:L,5,FALSE),"mmm") -> Mar
A5: I-1004 | B5: =VLOOKUP(A5,Raw_Data!A:L,6,FALSE) -> Ceiling fan | C5: =VLOOKUP(A5,Raw_Data!A:L,3,FALSE) -> Turkey | D5: =VLOOKUP(A5,Raw_Data!A:L,12,FALSE) -> 274 | E5: =VLOOKUP(A5,Raw_Data!A:L,11,FALSE) -> 2 | F5: =TEXT(VLOOKUP(A5,Raw_Data!A:L,5,FALSE),"mmm") -> Aug
A6: I-1005 | B6: =VLOOKUP(A6,Raw_Data!A:L,6,FALSE) -> Toaster | C6: =VLOOKUP(A6,Raw_Data!A:L,3,FALSE) -> Australia | D6: =VLOOKUP(A6,Raw_Data!A:L,12,FALSE) -> 1480 | E6: =VLOOKUP(A6,Raw_Data!A:L,11,FALSE) -> 40 | F6: =TEXT(VLOOKUP(A6,Raw_Data!A:L,5,FALSE),"mmm") -> Mar
A7: I-1006 | B7: =VLOOKUP(A7,Raw_Data!A:L,6,FALSE) -> Iron | C7: =VLOOKUP(A7,Raw_Data!A:L,3,FALSE) -> China | D7: =VLOOKUP(A7,Raw_Data!A:L,12,FALSE) -> 783 | E7: =VLOOKUP(A7,Raw_Data!A:L,11,FALSE) -> 27 | F7: =TEXT(VLOOKUP(A7,Raw_Data!A:L,5,FALSE),"mmm") -> Apr
A8: I-1007 | B8: =VLOOKUP(A8,Raw_Data!A:L,6,FALSE) -> Dishwasher | C8: =VLOOKUP(A8,Raw_Data!A:L,3,FALSE) -> Peru | D8: =VLOOKUP(A8,Raw_Data!A:L,12,FALSE) -> 0 | E8: =VLOOKUP(A8,Raw_Data!A:L,11,FALSE) -> 70 | F8: =TEXT(VLOOKUP(A8,Raw_Data!A:L,5,FALSE),"mmm") -> Jun
A9: I-1008 | B9: =VLOOKUP(A9,Raw_Data!A:L,6,FALSE) -> Iron | C9: =VLOOKUP(A9,Raw_Data!A:L,3,FALSE) -> Mexico | D9: =VLOOKUP(A9,Raw_Data!A:L,12,FALSE) -> 1176 | E9: =VLOOKUP(A9,Raw_Data!A:L,11,FALSE) -> 42 | F9: =TEXT(VLOOKUP(A9,Raw_Data!A:L,5,FALSE),"mmm") -> Jul
A10: I-1009 | B10: =VLOOKUP(A10,Raw_Data!A:L,6,FALSE) -> Washing Machine | C10: =VLOOKUP(A10,Raw_Data!A:L,3,FALSE) -> UK | D10: =VLOOKUP(A10,Raw_Data!A:L,12,FALSE) -> 57760 | E10: =VLOOKUP(A10,Raw_Data!A:L,11,FALSE) -> 76 | F10: =TEXT(VLOOKUP(A10,Raw_Data!A:L,5,FALSE),"mmm") -> Nov
A11: I-1010 | B11: =VLOOKUP(A11,Raw_Data!A:L,6,FALSE) -> Iron | C11: =VLOOKUP(A11,Raw_Data!A:L,3,FALSE) -> Peru | D11: =VLOOKUP(A11,Raw_Data!A:L,12,FALSE) -> 1904 | E11: =VLOOKUP(A11,Raw_Data!A:L,11,FALSE) -> 68 | F11: =TEXT(VLOOKUP(A11,Raw_Data!A:L,5,FALSE),"mmm") -> Jul
A12: I-1011 | B12: =VLOOKUP(A12,Raw_Data!A:L,6,FALSE) -> Refrigerator | C12: =VLOOKUP(A12,Raw_Data!A:L,3,FALSE) -> Saudi Arabia | D12: =VLOOKUP(A12,Raw_Data!A:L,12,FALSE) -> 26000 | E12: =VLOOKUP(A12,Raw_Data!A:L,11,FALSE) -> 52 | F12: =TEXT(VLOOKUP(A12,Raw_Data!A:L,5,FALSE),"mmm") -> Jul
... A2340: I-3339 | B2340: =VLOOKUP(A2340,Raw_Data!A:L,6,FALSE) -> Microwave | C2340: =VLOOKUP(A2340,Raw_Data!A:L,3,FALSE) -> China | D2340: =VLOOKUP(A2340,Raw_Data!A:L,12,FALSE) -> 1771 | E2340: =VLOOKUP(A2340,Raw_Data!A:L,11,FALSE) -> 23 | F2340: =TEXT(VLOOKUP(A2340,Raw_Data!A:L,5,FALSE),"mmm") -> Sep

Sheet Clean_Data
A1: Country | B1: Region | C1: Date | D1: Item | E1: List Price | F1: Quantity | G1: Revenue | H1: Month Name
A2: Russia | B2: EMEA | C2: 43261 | D2: Microwave | E2: 80 | F2: 83 | G2: 6557 | H2: Jun
A3: Canada | B3: NA | C3: 42117 | D3: Microwave | E3: 80 | F3: 8 | G3: 432 | H3: Apr
A4: Brazil | B4: LATAM | C4: 42798 | D4: Air conditioner | E4: 700 | F4: 91 | G4: 62426 | H4: Mar
A5: Turkey | B5: EMEA | C5: 43326 | D5: Ceiling fan | E5: 150 | F5: 2 | G5: 274 | H5: Aug
A6: Australia | B6: APAC | C6: 42066 | D6: Toaster | E6: 50 | F6: 40 | G6: 1480 | H6: Mar
A7: China | B7: APAC | C7: 42485 | D7: Iron | E7: 30 | F7: 27 | G7: 783 | H7: Apr
A8: Peru | B8: LATAM | C8: 42527 | D8: Dishwasher | E8: 500 | F8: 70 | H8: Jun
A9: Mexico | B9: LATAM | C9: 42557 | D9: Iron | E9: 30 | F9: 42 | G9: 1176 | H9: Jul
A10: UK | B10: EMEA | C10: 42320 | D10: Washing Machine | E10: 800 | F10: 76 | G10: 57760 | H10: Nov
A11: Peru | B11: LATAM | C11: 41829 | D11: Iron | E11: 30 | F11: 68 | G11: 1904 | H11: Jul
A12: Saudi Arabia | B12: EMEA | C12: 42926 | D12: Refrigerator | E12: 1000 | F12: 52 | G12: 26000 | H12: Jul
A13: Thailand | B13: APAC | C13: 41872 | D13: Air conditioner | E13: 700 | F13: 71 | G13: 48209 | H13: Aug
A14: Mexico | B14: LATAM | C14: 42250 | D14: Iron | E14: 30 | F14: 5 | G14: 140 | H14: Sep
A15: India | B15: APAC | C15: 41789 | D15: Oven | E15: 500 | F15: 57 | G15: 27930 | H15: May
A16: Australia | B16: APAC | C16: 43445 | D16: Washing Machine | E16: 800 | F16: 1 | G16: 672 | H16: Dec
A17: Vietnam | B17: APAC | C17: 42148 | D17: Microwave | E17: 80 | F17: 11 | G17: 858 | H17: May
A18: Israel | B18: EMEA | C18: 41802 | D18: Refrigerator | E18: 1000 | F18: 45 | G18: 27900 | H18: Jun
A19: Greece | B19: EMEA | C19: 43046 | D19: Oven | E19: 500 | F19: 59 | G19: 29500 | H19: Nov
A20: Canada | B20: NA | C20: 41946 | D20: Ceiling fan | E20: 150 | F20: 5 | G20: 750 | H20: Nov
... A2340: China | B2340: APAC | C2340: 42980 | D2340: Microwave | E2340: 80 | F2340: 23 | G2340: 1771 | H2340: Sep

Sheet Analysis
A1: Sales by Product | D1: Sales by Country | G1: Sales by Month
A2: Row Labels | B2: Sum of Revenue | D2: Row Labels | E2: Sum of Revenue | G2: Row Labels | H2: Sum of Revenue | J2: Sum of Revenue
A3: Refrigerator | B3: 7017020 | D3: USA | E3: 4514744 | G3: Jan | H3: 2962493 | J3: 34053377
A4: Washing Machine | B4: 6394336 | D4: China | E4: 1880862 | G4: Feb | H4: 2802567
A5: Air conditioner | B5: 5979071 | D5: Japan | E5: 1559747 | G5: Mar | H5: 2648290
A6: Oven | B6: 5030390 | D6: Israel | E6: 1497365 | G6: Apr | H6: 2990948 | J6: Row Labels | K6: Sum of Quantity
A7: Dishwasher | B7: 3781925 | D7: India | E7: 1495594 | G7: May | H7: 2464157 | J7: Iron | K7: 11948
A8: Vacuum Cleaner | B8: 2147734 | D8: UK | E8: 1446385 | G8: Jun | H8: 2903073 | J8: Washing Machine | K8: 10406
A9: Ceiling fan | B9: 1226203 | D9: Mexico | E9: 1357977 | G9: Jul | H9: 3388473 | J9: Oven | K9: 10167
A10: Microwave | B10: 709173 | D10: Russia | E10: 1077251 | G10: Aug | H10: 2780188 | J10: Microwave | K10: 9786
A11: Coffee grinder | B11: 592789 | D11: Canada | E11: 983389 | G11: Sep | H11: 2753757 | J11: Vacuum Cleaner | K11: 9555
A12: Toaster | B12: 430608 | D12: Czech Republic | E12: 917994 | G12: Oct | H12: 2737360 | J12: Toaster | K12: 9516
A13: Blender | B13: 420201 | D13: Colombia | E13: 868638 | G13: Nov | H13: 3319968 | J13: Air conditioner | K13: 9489
A14: Iron | B14: 323927 | D14: Argentina | E14: 850522 | G14: Dec | H14: 2302103 | J14: Coffee grinder | K14: 9455
A15: Grand Total | B15: 34053377 | D15: Spain | E15: 846485 | G15: Grand Total | H15: 34053377 | J15: Blender | K15: 9403
D16: Germany | E16: 833990 | J16: Refrigerator | K16: 9098
D17: Egypt | E17: 815822 | J17: Ceiling fan | K17: 9000
D18: Ireland | E18: 794325 | J18: Dishwasher | K18: 8676
D19: Thailand | E19: 792155 | J19: Grand Total | K19: 116499
D20: South Korea | E20: 770897
D21: South Africa | E21: 756696
D22: Australia | E22: 751901
D23: Netherlands | E23: 712488
D24: Turkey | E24: 704931
D25: Brazil | E25: 697834
D26: Poland | E26: 679492
D27: Romania | E27: 678401
D28: France | E28: 675122
D29: Malaysia | E29: 661663
D30: Greece | E30: 635003
D31: Saudi Arabia | E31: 630142
... D38: Grand Total | E38: 34053377

Sheet Dynamic_Dashboard
A16: Search Product: | C16: Refrigerator | D16: Official List Price: | F16: =VLOOKUP(C16, Clean_Data!D:E, 2,FALSE) -> 1000 | G16: Total Gross Revenue: | I16: =VLOOKUP(C16,Analysis!A:B, 2,FALSE) -> 7017020 | J16: Total Quantity: | L16: =VLOOKUP(C16,Analysis!J:K,2,FALSE) -> 9098
